Metadata-Version: 2.1
Name: Serializer-Deserializer
Version: 1.2
Summary: Serializer and Deserialize by models in messanger
Author-email: dim.chechulov@gmail.com
